MANIFEST.in
README.md
setup.cfg
setup.py
cpytraceafl/__init__.py
cpytraceafl/_testheadermodule.c
cpytraceafl/_tracehookmodule.c
cpytraceafl/cpytraceafl.h
cpytraceafl/rewriter.py
cpytraceafl/tracehook.py
cpytraceafl/version.py
cpytraceafl.egg-info/PKG-INFO
cpytraceafl.egg-info/SOURCES.txt
cpytraceafl.egg-info/dependency_links.txt
cpytraceafl.egg-info/requires.txt
cpytraceafl.egg-info/top_level.txt
tests/test_header.py
tests/test_rewriter.py
tests/test_tracehook.py