Metadata-Version: 2.1
Name: cpytraceafl
Version: 0.7.1
Summary: CPython bytecode instrumentation and forkserver tools for fuzzing python and mixed python/c code using AFL
Home-page: https://github.com/risicle/cpytraceafl
Author: Robert Scott
Author-email: code@humanleg.org.uk
License: MIT
Platform: UNKNOWN
Requires-Python: >=3.5, <3.9
